nebulae/__init__.py
nebulae/astro/__init__.py
nebulae/astro/craft.py
nebulae/astro/dock.py
nebulae/astro/hangar/__init__.py
nebulae/astro/hangar/Classic/__init__.py
nebulae/astro/hangar/Classic/resnet.py
nebulae/astro/hangar/Classic/vgg.py
nebulae/astro/hangar/GAN/__init__.py
nebulae/astro/hangar/GAN/architect.py
nebulae/astro/hangar/GAN/biggan.py
nebulae/astro/hangar/GAN/dcgan.py
nebulae/astro/hangar/GAN/fcgan.py
nebulae/astro/hangar/GAN/gan.py
nebulae/astro/hangar/GAN/infogan.py
nebulae/astro/hangar/GAN/resgan.py
nebulae/astro/hangar/GAN/wgan.py
nebulae/astro/hangar/GAN/wgan_div.py
nebulae/astro/hangar/Seq2Seq/__init__.py
nebulae/astro/hangar/Seq2Seq/architect.py
nebulae/astro/hangar/VAE/__init__.py
nebulae/astro/hangar/VAE/architect.py
nebulae/astro/hangar/VAE/dcvae.py
nebulae/astro/hangar/VAE/resvae.py
nebulae/astro/hangar/VAE/vae.py
nebulae/astro/hangar/VAE/vqvae.py
nebulae/fuel/__init__.py
nebulae/fuel/comburant.py
nebulae/fuel/generator.py
nebulae/fuel/tank.py
nebulae/kit/__init__.py
nebulae/kit/decorator.py
nebulae/kit/utility.py
nebulae/logs/__init__.py
nebulae/logs/inspector.py
nebulae/power/__init__.py
nebulae/power/engine.py
nebulae/power/multiverse.py
nebulae/power/time_machine.py
nebulae/rule/__init__.py
nebulae-0.6.27.dist-info/licenses/LICENSE
nebulae-0.6.27.dist-info/METADATA
nebulae-0.6.27.dist-info/WHEEL
nebulae-0.6.27.dist-info/top_level.txt
nebulae-0.6.27.dist-info/RECORD
